{
    "1521484025070620794": {
        "1523016978326098063": {
            "type": "auto",
            "roles": []
        },
        "1523019022029947052": {
            "type": "button",
            "roles": [
                {
                    "role_id": 1521484171778723951,
                    "label": "Lust",
                    "emoji": "💦"
                },
                {
                    "role_id": 1521484222421012600,
                    "label": "Greed",
                    "emoji": "💰"
                }
            ]
        },
        "1523021352058228737": {
            "type": "button",
            "roles": [
                {
                    "role_id": 1521484171778723951,
                    "label": "Lust",
                    "emoji": "💦"
                },
                {
                    "role_id": 1521484222421012600,
                    "label": "Greed",
                    "emoji": "💰"
                },
                {
                    "role_id": 1521484394949382264,
                    "label": "Envy",
                    "emoji": "🎭"
                },
                {
                    "role_id": 1521484265165160568,
                    "label": "Rajib",
                    "emoji": "🧍"
                },
                {
                    "role_id": 1521484265731133543,
                    "label": "Gluttony",
                    "emoji": "🍔"
                },
                {
                    "role_id": 1521485360465580053,
                    "label": "Sloth",
                    "emoji": "🦥"
                },
                {
                    "role_id": 1521484467372429342,
                    "label": "Red Devil",
                    "emoji": "👹"
                },
                {
                    "role_id": 1521484528911257751,
                    "label": "Pride",
                    "emoji": "👑"
                },
                {
                    "role_id": 1521485242974732308,
                    "label": "Wrath",
                    "emoji": "😡"
                }
            ]
        }
    }
}